{"skeleton":{"hash":"Uz1jxtDzHSpkdrECnva+rP8HEoA","spine":"3.6.52","width":569.78326,"height":292.719},"bones":[{"name":"root","x":0.0,"y":0.0,"rotation":0.0,"scaleX":-1.0,"scaleY":1.0,"shearX":0.0,"shearY":0.0,"length":0.0,"transform":"normal"},{"name":"weapon","parent":"root","x":-154.93756,"y":149.60274,"rotation":180.0,"scaleX":1.0,"scaleY":1.0,"shearX":0.0,"shearY":0.0,"length":30.820063,"transform":"normal"},{"name":"weapon2","parent":"root","x":-208.2625,"y":119.977776,"rotation":180.0,"scaleX":1.0,"scaleY":1.0,"shearX":0.0,"shearY":0.0,"length":33.632977,"transform":"normal"}],"slots":[{"dark":"00000000","blend":"normal","name":"body","bone":"weapon","color":"ffffffff","attachment":"body"},{"dark":"00000000","blend":"normal","name":"weapon2","bone":"weapon2","color":"ffffffff","attachment":"weapon2"},{"dark":"00000000","blend":"normal","name":"weapon1","bone":"weapon","color":"ffffffff","attachment":"weapon1"},{"dark":"00000000","blend":"normal","name":"zx01","bone":"weapon","color":"ffffffff","attachment":"zx01"}],"ik":[],"transform":[],"path":[],"skins":{"default":{"body":{"body":{"type":"region","path":"body","rotation":0.0,"x":-9.03669,"y":137.99896,"scaleX":1.0,"scaleY":1.0,"width":558.0,"height":288.0,"color":"ffffffff"}},"weapon2":{"weapon2":{"type":"region","path":"weapon2","rotation":-180.0,"x":9.77417,"y":-30.521187,"scaleX":1.0,"scaleY":1.0,"width":80.0,"height":71.0,"color":"ffffffff"}},"weapon1":{"weapon1":{"type":"region","path":"weapon1","rotation":-180.0,"x":11.099091,"y":-27.396225,"scaleX":1.0,"scaleY":1.0,"width":80.0,"height":72.0,"color":"ffffffff"}},"zx01":{"zx03":{"type":"region","path":"zx03","rotation":0.0,"x":-19.319946,"y":42.779964,"scaleX":1.0,"scaleY":1.0,"width":561.0,"height":107.0,"color":"ffffffff"},"zx01":{"type":"region","path":"zx01","rotation":0.0,"x":-19.319946,"y":42.779964,"scaleX":1.0,"scaleY":1.0,"width":561.0,"height":107.0,"color":"ffffffff"},"zx02":{"type":"region","path":"zx02","rotation":0.0,"x":-19.319946,"y":42.779964,"scaleX":1.0,"scaleY":1.0,"width":561.0,"height":107.0,"color":"ffffffff"}}}},"events":{"action":{"int":0,"float":0.0,"string":""},"finish":{"int":0,"float":0.0,"string":""}},"animations":{"attack":{"slots":{"zx01":{"attachment":[{"time":0.0,"name":"zx01"},{"time":0.1,"name":"zx02"},{"time":0.23333333,"name":"zx03"},{"time":0.33333334,"name":"zx01"}]}},"bones":{"root":{"rotate":[{"time":0.0,"angle":0.0,"curve":"stepped"},{"time":0.33333334,"angle":0.0}],"translate":[{"time":0.0,"x":0.0,"y":0.0,"curve":"stepped"},{"time":0.33333334,"x":0.0,"y":0.0}],"scale":[{"time":0.0,"x":1.0,"y":1.0,"curve":"stepped"},{"time":0.33333334,"x":1.0,"y":1.0}]},"weapon":{"rotate":[{"time":0.0,"angle":0.0,"curve":"stepped"},{"time":0.33333334,"angle":0.0}],"translate":[{"time":0.0,"x":0.0,"y":0.0,"curve":"stepped"},{"time":0.33333334,"x":0.0,"y":0.0}],"scale":[{"time":0.0,"x":1.0,"y":1.0,"curve":[0.25,0.0,0.75,1.0]},{"time":0.16666667,"x":1.4,"y":1.4,"curve":[0.25,0.0,0.75,1.0]},{"time":0.33333334,"x":1.0,"y":1.0}]},"weapon2":{"rotate":[{"time":0.0,"angle":0.0,"curve":"stepped"},{"time":0.33333334,"angle":0.0}],"translate":[{"time":0.0,"x":0.0,"y":0.0,"curve":"stepped"},{"time":0.33333334,"x":0.0,"y":0.0}],"scale":[{"time":0.0,"x":1.0,"y":1.0,"curve":[0.25,0.0,0.75,1.0]},{"time":0.16666667,"x":1.4,"y":1.4,"curve":[0.25,0.0,0.75,1.0]},{"time":0.33333334,"x":1.0,"y":1.0}]}},"events":[{"time":0.1,"name":"action","int":0,"float":0.0,"string":null},{"time":0.33333334,"name":"finish","int":0,"float":0.0,"string":null}]},"attack_left":{"slots":{"zx01":{"attachment":[{"time":0.0,"name":"zx01"},{"time":0.1,"name":"zx02"},{"time":0.23333333,"name":"zx03"},{"time":0.33333334,"name":"zx01"}]}},"bones":{"weapon":{"rotate":[{"time":0.0,"angle":0.0,"curve":"stepped"},{"time":0.33333334,"angle":0.0}],"translate":[{"time":0.0,"x":0.0,"y":0.0,"curve":"stepped"},{"time":0.33333334,"x":0.0,"y":0.0}],"scale":[{"time":0.0,"x":1.0,"y":1.0,"curve":[0.25,0.0,0.75,1.0]},{"time":0.16666667,"x":1.4,"y":1.4,"curve":[0.25,0.0,0.75,1.0]},{"time":0.33333334,"x":1.0,"y":1.0}]},"root":{"rotate":[{"time":0.0,"angle":0.0,"curve":"stepped"},{"time":0.33333334,"angle":0.0}],"translate":[{"time":0.0,"x":0.0,"y":0.0,"curve":"stepped"},{"time":0.33333334,"x":0.0,"y":0.0}],"scale":[{"time":0.0,"x":1.0,"y":1.0,"curve":"stepped"},{"time":0.33333334,"x":1.0,"y":1.0}]},"weapon2":{"rotate":[{"time":0.0,"angle":0.0,"curve":"stepped"},{"time":0.33333334,"angle":0.0}],"translate":[{"time":0.0,"x":0.0,"y":0.0,"curve":"stepped"},{"time":0.33333334,"x":0.0,"y":0.0}],"scale":[{"time":0.0,"x":1.0,"y":1.0,"curve":[0.25,0.0,0.75,1.0]},{"time":0.16666667,"x":1.4,"y":1.4,"curve":[0.25,0.0,0.75,1.0]},{"time":0.33333334,"x":1.0,"y":1.0}]}},"events":[{"time":0.1,"name":"action","int":0,"float":0.0,"string":null},{"time":0.33333334,"name":"finish","int":0,"float":0.0,"string":null}]},"move":{"slots":{"zx01":{"attachment":[{"time":0.0,"name":"zx01"},{"time":0.16666667,"name":"zx02"},{"time":0.33333334,"name":"zx03"},{"time":0.5,"name":"zx01"},{"time":0.6666667,"name":"zx02"},{"time":0.8333333,"name":"zx03"},{"time":1.0,"name":"zx01"},{"time":1.1666666,"name":"zx02"},{"time":1.3333334,"name":"zx03"},{"time":1.5,"name":"zx01"},{"time":1.6666666,"name":"zx02"},{"time":1.8333334,"name":"zx03"},{"time":2.0,"name":"zx01"}]}},"bones":{"root":{"rotate":[{"time":0.0,"angle":0.0,"curve":"stepped"},{"time":2.0,"angle":0.0}],"translate":[{"time":0.0,"x":0.0,"y":0.0,"curve":[0.25,0.0,0.75,1.0]},{"time":1.0,"x":0.0,"y":-20.0,"curve":[0.25,0.0,0.75,1.0]},{"time":2.0,"x":0.0,"y":0.0}],"scale":[{"time":0.0,"x":1.0,"y":1.0,"curve":"stepped"},{"time":2.0,"x":1.0,"y":1.0}]},"weapon2":{"rotate":[{"time":0.0,"angle":0.0,"curve":"stepped"},{"time":2.0,"angle":0.0}],"translate":[{"time":0.0,"x":0.0,"y":0.0,"curve":"stepped"},{"time":2.0,"x":0.0,"y":0.0}],"scale":[{"time":0.0,"x":1.0,"y":1.0,"curve":"stepped"},{"time":2.0,"x":1.0,"y":1.0}]},"weapon":{"rotate":[{"time":0.0,"angle":-359.88977,"curve":"stepped"},{"time":2.0,"angle":-359.88977}],"translate":[{"time":0.0,"x":0.0,"y":0.0,"curve":"stepped"},{"time":2.0,"x":0.0,"y":0.0}],"scale":[{"time":0.0,"x":1.0,"y":1.0,"curve":"stepped"},{"time":2.0,"x":1.0,"y":1.0}]}}},"move_left":{"slots":{"zx01":{"attachment":[{"time":0.0,"name":"zx01"},{"time":0.16666667,"name":"zx02"},{"time":0.33333334,"name":"zx03"},{"time":0.5,"name":"zx01"},{"time":0.6666667,"name":"zx02"},{"time":0.8333333,"name":"zx03"},{"time":1.0,"name":"zx01"},{"time":1.1666666,"name":"zx02"},{"time":1.3333334,"name":"zx03"},{"time":1.5,"name":"zx01"},{"time":1.6666666,"name":"zx02"},{"time":1.8333334,"name":"zx03"},{"time":2.0,"name":"zx01"}]}},"bones":{"weapon2":{"rotate":[{"time":0.0,"angle":0.0,"curve":"stepped"},{"time":2.0,"angle":0.0}],"translate":[{"time":0.0,"x":0.0,"y":0.0,"curve":"stepped"},{"time":2.0,"x":0.0,"y":0.0}],"scale":[{"time":0.0,"x":1.0,"y":1.0,"curve":"stepped"},{"time":2.0,"x":1.0,"y":1.0}]},"root":{"rotate":[{"time":0.0,"angle":0.0,"curve":"stepped"},{"time":2.0,"angle":0.0}],"translate":[{"time":0.0,"x":0.0,"y":0.0,"curve":[0.25,0.0,0.75,1.0]},{"time":1.0,"x":0.0,"y":-20.0,"curve":[0.25,0.0,0.75,1.0]},{"time":2.0,"x":0.0,"y":0.0}],"scale":[{"time":0.0,"x":1.0,"y":1.0,"curve":"stepped"},{"time":2.0,"x":1.0,"y":1.0}]},"weapon":{"rotate":[{"time":0.0,"angle":-359.88977,"curve":"stepped"},{"time":2.0,"angle":-359.88977}],"translate":[{"time":0.0,"x":0.0,"y":0.0,"curve":"stepped"},{"time":2.0,"x":0.0,"y":0.0}],"scale":[{"time":0.0,"x":1.0,"y":1.0,"curve":"stepped"},{"time":2.0,"x":1.0,"y":1.0}]}}}}}